python_southtyrol_weather/__init__.py
python_southtyrol_weather/endpoints/weatherstation.py
python_southtyrol_weather-0.0.1.dist-info/METADATA
python_southtyrol_weather-0.0.1.dist-info/WHEEL
python_southtyrol_weather-0.0.1.dist-info/licenses/LICENSE
python_southtyrol_weather-0.0.1.dist-info/RECORD
