Metadata-Version: 2.4
Name: python-southtyrol-weather
Version: 0.0.1
Summary: Python library that provides real-time and forecast weather for southtyrol using the Open Data Hub API
Project-URL: Homepage, https://github.com/probert94/python-southtyrol-weather
Author: Robert Pattis
License-Expression: MIT
License-File: LICENSE
Keywords: api,southtyrol,weather
Requires-Python: >=3.10
Requires-Dist: aiohttp>=3.11
